[{"symbol": "CSX", "date": "2022-06-30", "stockPrice": 29.0599995, "numberOfShares": 2141241136, "marketCapitalization": 62224466341.53943, "minusCashAndCashEquivalents": 724000000, "addTotalDebt": 16683000000, "enterpriseValue": 78183466341.53943}, {"symbol": "CSX", "date": "2022-03-31", "stockPrice": 37.4500008, "numberOfShares": 2174259952, "marketCapitalization": 81426036941.80795, "minusCashAndCashEquivalents": 1936000000, "addTotalDebt": 16812000000, "enterpriseValue": 96302036941.80795}, {"symbol": "CSX", "date": "2021-12-31", "stockPrice": 37.5999985, "numberOfShares": 2202000000, "marketCapitalization": 82795196697, "minusCashAndCashEquivalents": 2239000000, "addTotalDebt": 16844000000, "enterpriseValue": 97400196697}, {"symbol": "CSX", "date": "2021-09-30", "stockPrice": 29.7399998, "numberOfShares": 2217983411, "marketCapitalization": 65962826199.54332, "minusCashAndCashEquivalents": 2179000000, "addTotalDebt": 16875000000, "enterpriseValue": 80658826199.54332}, {"symbol": "CSX", "date": "2021-06-30", "stockPrice": 32.0800018, "numberOfShares": 2254495910, "marketCapitalization": 72324232850.89264, "minusCashAndCashEquivalents": 2986000000, "addTotalDebt": 16801000000, "enterpriseValue": 86139232850.89264}, {"symbol": "CSX", "date": "2021-03-31", "stockPrice": 32.1399994, "numberOfShares": 2272200648, "marketCapitalization": 73028527463.39961, "minusCashAndCashEquivalents": 2955000000, "addTotalDebt": 16800000000, "enterpriseValue": 86873527463.39961}, {"symbol": "CSX", "date": "2020-12-31", "stockPrice": 30.25, "numberOfShares": 2289000000, "marketCapitalization": 69242250000, "minusCashAndCashEquivalents": 3129000000, "addTotalDebt": 17160000000, "enterpriseValue": 83273250000}, {"symbol": "CSX", "date": "2020-09-30", "stockPrice": 25.8899994, "numberOfShares": 2294324874, "marketCapitalization": 59400069611.265076, "minusCashAndCashEquivalents": 2898000000, "addTotalDebt": 16967000000, "enterpriseValue": 73469069611.26508}, {"symbol": "CSX", "date": "2020-06-30", "stockPrice": 23.2466679, "numberOfShares": 2295157647, "marketCapitalization": 53354767597.95443, "minusCashAndCashEquivalents": 2391000000, "addTotalDebt": 16987000000, "enterpriseValue": 67950767597.95443}, {"symbol": "CSX", "date": "2020-03-31", "stockPrice": 19.1000004, "numberOfShares": 2296397682, "marketCapitalization": 43861196644.75907, "minusCashAndCashEquivalents": 1995000000, "addTotalDebt": 16732000000, "enterpriseValue": 58598196644.75907}, {"symbol": "CSX", "date": "2019-12-31", "stockPrice": 24.1200008, "numberOfShares": 2319000000, "marketCapitalization": 55934281855.2, "minusCashAndCashEquivalents": 958000000, "addTotalDebt": 16238000000, "enterpriseValue": 71214281855.2}, {"symbol": "CSX", "date": "2019-09-30", "stockPrice": 23.0900002, "numberOfShares": 2347009638, "marketCapitalization": 54192453010.82192, "minusCashAndCashEquivalents": 1521000000, "addTotalDebt": 16796000000, "enterpriseValue": 69467453010.82193}, {"symbol": "CSX", "date": "2019-06-30", "stockPrice": 26.2099991, "numberOfShares": 2394527424, "marketCapitalization": 62760561627.965324, "minusCashAndCashEquivalents": 853000000, "addTotalDebt": 15826000000, "enterpriseValue": 77733561627.96533}, {"symbol": "CSX", "date": "2019-03-31", "stockPrice": 25.5666676, "numberOfShares": 2427490998, "marketCapitalization": 62062855447.85826, "minusCashAndCashEquivalents": 1188000000, "addTotalDebt": 15819000000, "enterpriseValue": 76693855447.85826}, {"symbol": "CSX", "date": "2018-12-31", "stockPrice": 20.7099991, "numberOfShares": 2454000000, "marketCapitalization": 50822337791.4, "minusCashAndCashEquivalents": 858000000, "addTotalDebt": 14757000000, "enterpriseValue": 64721337791.4}, {"symbol": "CSX", "date": "2018-09-30", "stockPrice": 25.0100002, "numberOfShares": 2533261083, "marketCapitalization": 63356860192.482216, "minusCashAndCashEquivalents": 663000000, "addTotalDebt": 13772000000, "enterpriseValue": 76465860192.48221}, {"symbol": "CSX", "date": "2018-06-30", "stockPrice": 21.2600002, "numberOfShares": 2576431671, "marketCapitalization": 54774937840.74634, "minusCashAndCashEquivalents": 1320000000, "addTotalDebt": 13788000000, "enterpriseValue": 67242937840.74634}, {"symbol": "CSX", "date": "2018-03-31", "stockPrice": 18.2466679, "numberOfShares": 2626060638, "marketCapitalization": 47916856346.848114, "minusCashAndCashEquivalents": 1980000000, "addTotalDebt": 13787000000, "enterpriseValue": 59723856346.848114}, {"symbol": "CSX", "date": "2017-12-31", "stockPrice": 18.7800007, "numberOfShares": 2670000000, "marketCapitalization": 50142601869, "minusCashAndCashEquivalents": 401000000, "addTotalDebt": 11809000000, "enterpriseValue": 61550601869}, {"symbol": "CSX", "date": "2017-09-30", "stockPrice": 18.0866661, "numberOfShares": 2681169249, "marketCapitalization": 48493412964.250755, "minusCashAndCashEquivalents": 591000000, "addTotalDebt": 11807000000, "enterpriseValue": 59709412964.250755}, {"symbol": "CSX", "date": "2017-06-30", "stockPrice": 18.1866665, "numberOfShares": 2739939030, "marketCapitalization": 49830357368.9435, "minusCashAndCashEquivalents": 620000000, "addTotalDebt": 11825000000, "enterpriseValue": 61035357368.9435}, {"symbol": "CSX", "date": "2017-03-31", "stockPrice": 15.5166674, "numberOfShares": 2768061432, "marketCapitalization": 42951088583.11172, "minusCashAndCashEquivalents": 930000000, "addTotalDebt": 11294000000, "enterpriseValue": 53315088583.11172}, {"symbol": "CSX", "date": "2016-12-30", "stockPrice": 11.9766674, "numberOfShares": 2784000000, "marketCapitalization": 33343042041.600002, "minusCashAndCashEquivalents": 603000000, "addTotalDebt": 11293000000, "enterpriseValue": 44033042041.600006}, {"symbol": "CSX", "date": "2016-09-23", "stockPrice": 9.8800001, "numberOfShares": 2809983336, "marketCapitalization": 27762635640.678333, "minusCashAndCashEquivalents": 603000000, "addTotalDebt": 10519000000, "enterpriseValue": 37678635640.67833}, {"symbol": "CSX", "date": "2016-06-24", "stockPrice": 8.5666666, "numberOfShares": 2837972835, "marketCapitalization": 24311967097.30181, "minusCashAndCashEquivalents": 566000000, "addTotalDebt": 10537000000, "enterpriseValue": 34282967097.30181}, {"symbol": "CSX", "date": "2016-03-25", "stockPrice": 8.7233334, "numberOfShares": 2867601246, "marketCapitalization": 25015041727.113415, "minusCashAndCashEquivalents": 731000000, "addTotalDebt": 10536000000, "enterpriseValue": 34820041727.11342}, {"symbol": "CSX", "date": "2015-12-25", "stockPrice": 8.71, "numberOfShares": 2898000000, "marketCapitalization": 25241580000.000004, "minusCashAndCashEquivalents": 628000000, "addTotalDebt": 10535000000, "enterpriseValue": 35148580000}, {"symbol": "CSX", "date": "2015-09-25", "stockPrice": 8.8400002, "numberOfShares": 2924834373, "marketCapitalization": 25855536442.286877, "minusCashAndCashEquivalents": 541000000, "addTotalDebt": 10106000000, "enterpriseValue": 35420536442.28688}, {"symbol": "CSX", "date": "2015-06-26", "stockPrice": 11.2233334, "numberOfShares": 2951211738, "marketCapitalization": 33122433269.567448, "minusCashAndCashEquivalents": 438000000, "addTotalDebt": 10125000000, "enterpriseValue": 42809433269.567444}, {"symbol": "CSX", "date": "2015-03-27", "stockPrice": 11.0666666, "numberOfShares": 2963944224, "marketCapitalization": 32800982548.003716, "minusCashAndCashEquivalents": 561000000, "addTotalDebt": 9741000000, "enterpriseValue": 41980982548.003716}, {"symbol": "CSX", "date": "2014-12-26", "stockPrice": 12.2266674, "numberOfShares": 2976000000, "marketCapitalization": 36386562182.4, "minusCashAndCashEquivalents": 669000000, "addTotalDebt": 9742000000, "enterpriseValue": 45459562182.4}, {"symbol": "CSX", "date": "2014-09-26", "stockPrice": 10.7733326, "numberOfShares": 2986191909, "marketCapitalization": 32171238643.085934, "minusCashAndCashEquivalents": 479000000, "addTotalDebt": 9617000000, "enterpriseValue": 41309238643.08594}, {"symbol": "CSX", "date": "2014-06-27", "stockPrice": 10.2566671, "numberOfShares": 3009000000, "marketCapitalization": 30862311303.899998, "minusCashAndCashEquivalents": 573000000, "addTotalDebt": 9309000000, "enterpriseValue": 39598311303.899994}, {"symbol": "CSX", "date": "2014-03-28", "stockPrice": 9.5266666, "numberOfShares": 3013087767, "marketCapitalization": 28704682592.747482, "minusCashAndCashEquivalents": 475000000, "addTotalDebt": 9346000000, "enterpriseValue": 37575682592.74748}, {"symbol": "CSX", "date": "2013-12-27", "stockPrice": 9.4300003, "numberOfShares": 3027000000, "marketCapitalization": 28544610908.1, "minusCashAndCashEquivalents": 592000000, "addTotalDebt": 9555000000, "enterpriseValue": 37507610908.1}, {"symbol": "CSX", "date": "2013-09-27", "stockPrice": 8.6166668, "numberOfShares": 3041023083, "marketCapitalization": 26203482637.319748, "minusCashAndCashEquivalents": 591000000, "addTotalDebt": 9051000000, "enterpriseValue": 34663482637.31975}, {"symbol": "CSX", "date": "2013-06-28", "stockPrice": 7.73, "numberOfShares": 3056511939, "marketCapitalization": 23626837288.47, "minusCashAndCashEquivalents": 614000000, "addTotalDebt": 9375000000, "enterpriseValue": 32387837288.47}, {"symbol": "CSX", "date": "2013-03-29", "stockPrice": 8.21, "numberOfShares": 3065881890, "marketCapitalization": 25170890316.9, "minusCashAndCashEquivalents": 705000000, "addTotalDebt": 9418000000, "enterpriseValue": 33883890316.9}, {"symbol": "CSX", "date": "2012-12-28", "stockPrice": 6.4766669, "numberOfShares": 3060000000, "marketCapitalization": 19818600714, "minusCashAndCashEquivalents": 784000000, "addTotalDebt": 9832000000, "enterpriseValue": 28866600714}, {"symbol": "CSX", "date": "2012-09-28", "stockPrice": 6.916667, "numberOfShares": 3114000000, "marketCapitalization": 21538501038, "minusCashAndCashEquivalents": 693000000, "addTotalDebt": 9063000000, "enterpriseValue": 29908501038}, {"symbol": "CSX", "date": "2012-06-29", "stockPrice": 7.4533329, "numberOfShares": 3119966010, "marketCapitalization": 23254145309.21473, "minusCashAndCashEquivalents": 642000000, "addTotalDebt": 9089000000, "enterpriseValue": 31701145309.21473}, {"symbol": "CSX", "date": "2012-03-30", "stockPrice": 7.1733332, "numberOfShares": 3117474186, "marketCapitalization": 22362681078.576775, "minusCashAndCashEquivalents": 627000000, "addTotalDebt": 9125000000, "enterpriseValue": 30860681078.576775}, {"symbol": "CSX", "date": "2011-12-30", "stockPrice": 7.02, "numberOfShares": 3165600000, "marketCapitalization": 22222512000, "minusCashAndCashEquivalents": 783000000, "addTotalDebt": 9241000000, "enterpriseValue": 30680512000}, {"symbol": "CSX", "date": "2011-09-30", "stockPrice": 6.2233329, "numberOfShares": 3149859060, "marketCapitalization": 19602621518.461075, "minusCashAndCashEquivalents": 580000000, "addTotalDebt": 8654000000, "enterpriseValue": 27676621518.461075}, {"symbol": "CSX", "date": "2011-07-01", "stockPrice": 8.9366674, "numberOfShares": 3285844518, "marketCapitalization": 29364499585.47931, "minusCashAndCashEquivalents": 1252000000, "addTotalDebt": 8680000000, "enterpriseValue": 36792499585.47931}, {"symbol": "CSX", "date": "2011-04-01", "stockPrice": 8.8211107, "numberOfShares": 3308294079, "marketCapitalization": 29182828299.013546, "minusCashAndCashEquivalents": 534000000, "addTotalDebt": 8140000000, "enterpriseValue": 36788828299.01355}, {"symbol": "CSX", "date": "2010-12-31", "stockPrice": 7.1788888, "numberOfShares": 3436500000, "marketCapitalization": 24670251361.2, "minusCashAndCashEquivalents": 1292000000, "addTotalDebt": 8664000000, "enterpriseValue": 32042251361.2}, {"symbol": "CSX", "date": "2010-09-24", "stockPrice": 6.2377782, "numberOfShares": 3367661589, "marketCapitalization": 21006726044.84156, "minusCashAndCashEquivalents": 636000000, "addTotalDebt": 7902000000, "enterpriseValue": 28272726044.84156}, {"symbol": "CSX", "date": "2010-06-25", "stockPrice": 5.8055558, "numberOfShares": 3477519000, "marketCapitalization": 20188930600.0602, "minusCashAndCashEquivalents": 633000000, "addTotalDebt": 7934000000, "enterpriseValue": 27489930600.0602}, {"symbol": "CSX", "date": "2010-03-26", "stockPrice": 5.665556, "numberOfShares": 3503033685, "marketCapitalization": 19846633512.25386, "minusCashAndCashEquivalents": 993000000, "addTotalDebt": 7989000000, "enterpriseValue": 26842633512.25386}, {"symbol": "CSX", "date": "2009-12-25", "stockPrice": 5.5999999, "numberOfShares": 3572400000, "marketCapitalization": 20005439642.760002, "minusCashAndCashEquivalents": 1029000000, "addTotalDebt": 8008000000, "enterpriseValue": 26984439642.760002}, {"symbol": "CSX", "date": "2009-09-25", "stockPrice": 4.7577782, "numberOfShares": 3524346000, "marketCapitalization": 16768056568.0572, "minusCashAndCashEquivalents": 1240000000, "addTotalDebt": 8222000000, "enterpriseValue": 23750056568.057198}]